azure/mgmt/servicebus/__init__.py
azure/mgmt/servicebus/_configuration.py
azure/mgmt/servicebus/_serialization.py
azure/mgmt/servicebus/_service_bus_management_client.py
azure/mgmt/servicebus/_version.py
azure/mgmt/servicebus/models.py
azure/mgmt/servicebus/py.typed
azure/mgmt/servicebus/aio/__init__.py
azure/mgmt/servicebus/aio/_configuration.py
azure/mgmt/servicebus/aio/_service_bus_management_client.py
azure/mgmt/servicebus/v2015_08_01/__init__.py
azure/mgmt/servicebus/v2015_08_01/_configuration.py
azure/mgmt/servicebus/v2015_08_01/_patch.py
azure/mgmt/servicebus/v2015_08_01/_service_bus_management_client.py
azure/mgmt/servicebus/v2015_08_01/_version.py
azure/mgmt/servicebus/v2015_08_01/py.typed
azure/mgmt/servicebus/v2015_08_01/aio/__init__.py
azure/mgmt/servicebus/v2015_08_01/aio/_configuration.py
azure/mgmt/servicebus/v2015_08_01/aio/_patch.py
azure/mgmt/servicebus/v2015_08_01/aio/_service_bus_management_client.py
azure/mgmt/servicebus/v2015_08_01/aio/operations/__init__.py
azure/mgmt/servicebus/v2015_08_01/aio/operations/_namespaces_operations.py
azure/mgmt/servicebus/v2015_08_01/aio/operations/_operations.py
azure/mgmt/servicebus/v2015_08_01/aio/operations/_patch.py
azure/mgmt/servicebus/v2015_08_01/aio/operations/_queues_operations.py
azure/mgmt/servicebus/v2015_08_01/aio/operations/_subscriptions_operations.py
azure/mgmt/servicebus/v2015_08_01/aio/operations/_topics_operations.py
azure/mgmt/servicebus/v2015_08_01/models/__init__.py
azure/mgmt/servicebus/v2015_08_01/models/_models_py3.py
azure/mgmt/servicebus/v2015_08_01/models/_patch.py
azure/mgmt/servicebus/v2015_08_01/models/_service_bus_management_client_enums.py
azure/mgmt/servicebus/v2015_08_01/operations/__init__.py
azure/mgmt/servicebus/v2015_08_01/operations/_namespaces_operations.py
azure/mgmt/servicebus/v2015_08_01/operations/_operations.py
azure/mgmt/servicebus/v2015_08_01/operations/_patch.py
azure/mgmt/servicebus/v2015_08_01/operations/_queues_operations.py
azure_mgmt_servicebus-8.2.1.dist-info/LICENSE
azure_mgmt_servicebus-8.2.1.dist-info/METADATA
azure_mgmt_servicebus-8.2.1.dist-info/WHEEL
azure_mgmt_servicebus-8.2.1.dist-info/top_level.txt
azure_mgmt_servicebus-8.2.1.dist-info/RECORD
